{
    "common": {
        "name": "heatingcontrol",
        "version": "2.9.0",
        "news": {
            "2.9.0": {
                "en": "notification and extended actor handling added",
                "de": "Benachrichtigung und erweiterte Akteursbehandlung hinzugefügt",
                "ru": "добавлены уведомления и расширенная обработка акторов",
                "pt": "adição de notificação e manipulação estendida de atores",
                "nl": "melding en uitgebreide afhandeling van acteurs toegevoegd",
                "fr": "notification et gestion étendue des acteurs ajoutées",
                "it": "aggiunta la notifica e la gestione estesa dell'attore",
                "es": "Se agregaron notificaciones y manejo extendido de actores.",
                "pl": "dodano powiadomienie i rozszerzoną obsługę aktorów",
                "zh-cn": "添加了通知和扩展的演员处理"
            },
            "2.8.7": {
                "en": "bug fix open window handling if thermostat reduces temperature",
                "de": "Fehlerbehebung beim Öffnen des Fensters, wenn der Thermostat die Temperatur senkt",
                "ru": "исправлена ​​ошибка обработки открытого окна, если термостат снижает температуру",
                "pt": "correção de bug manipulação de janela aberta se o termostato reduzir a temperatura",
                "nl": "bug fix open raam behandeling als thermostaat de temperatuur verlaagt",
                "fr": "correction d'un bogue gestion de la fenêtre ouverte si le thermostat réduit la température",
                "it": "correzione bug gestione finestra aperta se il termostato riduce la temperatura",
                "es": "corrección de errores manejo de ventanas abiertas si el termostato reduce la temperatura",
                "pl": "naprawa błędu obsługa otwartego okna, jeśli termostat obniża temperaturę",
                "zh-cn": "如果恒温器降低温度，则修复打开窗口处理的错误"
            },
            "2.8.6": {
                "en": "bug fix window handling",
                "de": "Fehlerbehebung bei der Fensterbehandlung",
                "ru": "обработка окна исправления ошибки",
                "pt": "manipulação de janela de correção de bug",
                "nl": "bug fix venster behandeling",
                "fr": "gestion des fenêtres de correction de bogues",
                "it": "gestione della finestra di correzione dei bug",
                "es": "manejo de ventanas de corrección de errores",
                "pl": "naprawa błędów obsługi okien",
                "zh-cn": "错误修复窗口处理"
            },
            "2.8.5": {
                "en": "inter thermostat delay added",
                "de": "Interthermostatverzögerung hinzugefügt",
                "ru": "добавлена ​​межтермостатическая задержка",
                "pt": "atraso entre termostato adicionado",
                "nl": "inter thermostaat vertraging toegevoegd",
                "fr": "délai inter thermostat ajouté",
                "it": "ritardo tra termostato aggiunto",
                "es": "retardo intertermostato agregado",
                "pl": "Dodano opóźnienie między termostatem",
                "zh-cn": "添加了恒温器间延迟"
            },
            "2.8.4": {
                "en": "new datapoint to show current profile temperature; inter actuator delay",
                "de": "neuer Datenpunkt zur Anzeige der aktuellen Profiltemperatur; ",
                "ru": "новая точка данных для отображения текущей температуры профиля; ",
                "pt": "novo ponto de dados para mostrar a temperatura atual do perfil; ",
                "nl": "nieuw datapunt om de huidige profieltemperatuur weer te geven; ",
                "fr": "nouveau point de données pour afficher la température actuelle du profil ; ",
                "it": "nuovo punto dati per mostrare la temperatura del profilo corrente; ",
                "es": "nuevo punto de datos para mostrar la temperatura del perfil actual; ",
                "pl": "nowy punkt danych pokazujący aktualną temperaturę profilu; ",
                "zh-cn": "显示当前温度曲线的新数据点；"
            },
            "2.8.3": {
                "en": "Loading the configuration fixed",
                "de": "Laden der Konfiguration behoben",
                "ru": "Исправлена ​​загрузка конфигурации",
                "pt": "Carregando a configuração corrigida",
                "nl": "Laden van de configuratie vast",
                "fr": "Chargement de la configuration corrigé",
                "it": "Caricamento della configurazione risolto",
                "es": "Cargando la configuración fija",
                "pl": "Naprawiono ładowanie konfiguracji",
                "zh-cn": "加载配置固定"
            },
            "2.8.2": {
                "en": "absent and VacationAbsent exchanged to check reduced mode",
                "de": "abwesend und VacationAbsent ausgetauscht, um den reduzierten Modus zu überprüfen",
                "ru": "absent и VacationAbsent заменены, чтобы проверить сокращенный режим",
                "pt": "ausente e VacationAbsent trocados para verificar o modo reduzido",
                "nl": "afwezig en VakantieAfwezig uitgewisseld om de gereduceerde modus te controleren",
                "fr": "absent et VacationAbsent échangés pour vérifier le mode réduit",
                "it": "assente e VacanzaAssente scambiati per verifica modalità ridotta",
                "es": "ausente y VacationAbsent intercambiado para comprobar el modo reducido",
                "pl": "nieobecny i VacationAbsent wymienione, aby sprawdzić tryb zredukowany",
                "zh-cn": "缺席和 VacationAbsent 交换检查减少模式"
            },
            "2.8.1": {
                "en": "show internal and external temperature sensors in room status",
                "de": "interne und externe Temperatursensoren im Raumstatus anzeigen",
                "ru": "показывать внутренние и внешние датчики температуры в состоянии помещения",
                "pt": "mostrar sensores de temperatura interna e externa no status da sala",
                "nl": "toon interne en externe temperatuursensoren in kamerstatus",
                "fr": "afficher les capteurs de température internes et externes dans l'état de la pièce",
                "it": "mostra i sensori di temperatura interna ed esterna nello stato della stanza",
                "es": "mostrar sensores de temperatura internos y externos en el estado de la habitación",
                "pl": "pokaż wewnętrzne i zewnętrzne czujniki temperatury w stanie pokoju",
                "zh-cn": "在房间状态下显示内部和外部温度传感器"
            },
            "2.8.0": {
                "en": "differrent regulators for actor handling added",
                "de": "verschiedene Regler für Schauspielerhandhabung hinzugefügt",
                "ru": "добавлены различные регуляторы для работы с актерами",
                "pt": "reguladores diferentes para manipulação de ator adicionado",
                "nl": "verschillende regelgevers voor het omgaan met acteurs toegevoegd",
                "fr": "différents régulateurs pour la gestion des acteurs ajoutés",
                "it": "aggiunti diversi regolatori per la gestione degli attori",
                "es": "Se agregaron diferentes reguladores para el manejo de actores.",
                "pl": "dodano różne regulatory do obsługi aktorów",
                "zh-cn": "添加了不同的演员处理监管机构"
            },
            "2.7.2": {
                "en": "some bug fixes, see readme",
                "de": "einige Fehlerbehebungen, siehe Readme",
                "ru": "исправления ошибок, см. readme",
                "pt": "algumas correções de bugs, veja leia-me",
                "nl": "enkele bugfixes, zie readme",
                "fr": "quelques corrections de bugs, voir readme",
                "it": "alcune correzioni di bug, vedere readme",
                "es": "algunas correcciones de errores, vea el archivo Léame",
                "pl": "kilka poprawek błędów, zobacz readme",
                "zh-cn": "一些错误修复，请参阅自述文件"
            },
            "2.7.1": {
                "en": "change of override in manual mode is mssing",
                "de": "Änderung des Overrides im manuellen Modus wird gesendet",
                "ru": "смена переопределения в ручном режиме не выполняется",
                "pt": "a mudança de substituição no modo manual está em uso",
                "nl": "wijziging van opheffing in handmatige modus is mssing",
                "fr": "le changement d'override en mode manuel est mssing",
                "it": "la modifica dell'override in modalità manuale sta suonando",
                "es": "el cambio de anulación en modo manual está fallando",
                "pl": "brak zmiany nadpisania w trybie ręcznym",
                "zh-cn": "手动模式下的覆盖更改是 mssing"
            },
            "2.7.0": {
                "en": "limit for additional temp sensors added",
                "de": "Limit für zusätzliche Temperatursensoren hinzugefügt",
                "ru": "добавлен предел для дополнительных датчиков температуры",
                "pt": "limite para sensores de temperatura adicionais adicionados",
                "nl": "limiet voor extra temperatuursensoren toegevoegd",
                "fr": "limite pour les capteurs de température supplémentaires ajoutés",
                "it": "limite per ulteriori sensori di temperatura aggiunti",
                "es": "límite para sensores de temperatura adicionales agregado",
                "pl": "dodano limit dla dodatkowych czujników temperatury",
                "zh-cn": "添加了额外温度传感器的限制"
            },
            "2.6.2": {
                "en": "bug fix isActive not ignored",
                "de": "Bugfix isActive wird nicht ignoriert",
                "ru": "исправление ошибки isActive не игнорируется",
                "pt": "correção de bug isActive not ignore",
                "nl": "bug fix isActive niet genegeerd",
                "fr": "correction de bogue isActive non ignoré",
                "it": "la correzione del bug èAttivo non ignorato",
                "es": "corrección de errores isActive no ignorado",
                "pl": "naprawa błędu jest Aktywna nie jest ignorowana",
                "zh-cn": "错误修复 isActive 未被忽略"
            }
        },
        "title": "HeatingControl",
        "titleLang": {
            "en": "Heating Control",
            "de": "Heizungsregelung",
            "ru": "Управление отоплением",
            "pt": "Controle de aquecimento",
            "nl": "Verwarmingregeling",
            "fr": "Contrôle du chauffage",
            "it": "Controllo del riscaldamento",
            "es": "Control de calentamiento",
            "pl": "Kontrola ogrzewania",
            "zh-cn": "加热控制"
        },
        "desc": {
            "en": "Heating Control",
            "de": "Heizungsregelung",
            "ru": "Управление отоплением",
            "pt": "Controle de aquecimento",
            "nl": "Verwarmingregeling",
            "fr": "Contrôle du chauffage",
            "it": "Controllo del riscaldamento",
            "es": "Control de calentamiento",
            "pl": "Kontrola ogrzewania",
            "zh-cn": "加热控制"
        },
        "platform": "Javascript/Node.js",
        "mode": "daemon",
        "icon": "heatingcontrol.png",
        "enabled": true,
        "messagebox": true,
        "extIcon": "https://raw.githubusercontent.com/rg-engineering/ioBroker.heatingcontrol/master/admin/heatingcontrol.png",
        "keywords": [
            "heating"
        ],
        "readme": "https://github.com/rg-engineering/ioBroker.heatingcontrol/blob/master/README.md",
        "loglevel": "info",
        "stopBeforeUpdate": true,
        "type": "climate-control",
        "license": "MIT",
        "materialize": true,
        "dependencies": [
            {
                "js-controller": ">=2.0.0"
            }
        ],
        "plugins": {
            "sentry": {
                "dsn": "https://5799cf9f70cb43c7a761192a5f35d419@o390433.ingest.sentry.io/5434781"
            }
        },
        "compact": true,
        "authors": [
            {
                "name": "René G.",
                "email": "info@rg-engineering.eu"
            }
        ],
        "contributors": [
            "DutchmanNL <rdrozda86@gmail.com>"
        ],
        "connectionType": "local",
        "dataSource": "push",
        "adminUI": {
            "config": "materialize"
        }
    },
    "native": {
        "devices": [],
        "rooms": [],
        "UseActors": false,
        "Gewerk": "Heizung",
        "ProfileType": 1,
        "NumberOfProfiles": 1,
        "NumberOfPeriods": 5,
        "timezone": "Europe/Berlin",
        "UseActorsIfNotHeating": 1,
        "UseActorsIfNoThermostat": 1,
        "Path2FeiertagAdapter": "",
        "Path2PresentDP": "",
        "PublicHolidayLikeSunday": true,
        "UseFixHeatingPeriod": false,
        "FixHeatingPeriodStart": "01.10.",
        "FixHeatingPeriodEnd": "31.03.",
        "TemperatureDecrease": 3,
        "Path2VacationDP": "",
        "Path2HolidayPresentDP": "",
        "Path2GuestsPresentDP": "",
        "Path2PresentDPType": 1,
        "Path2PartyNowDP": "",
        "SensorOpenDelay": 0,
        "UseMinTempPerRoom": false,
        "ThermostatModeIfNoHeatingperiod": 3,
        "FixTempIfNoHeatingPeriod": "15;",
        "UseChangesFromThermostat": 1,
        "UseVisFromPittini": false,
        "SensorCloseDelay": 0,
        "PittiniPathImageWindowOpen": "",
        "PittiniPathImageWindowClosed": "",
        "ActorBeforeOnDelay": 0,
        "ActorBeforeOffDelay": 0,
        "Path2PresentDPLimit": 0,
        "Path2GuestsPresentDPType": 1,
        "Path2GuestsPresentDPLimit": 0,
        "Path2PartyNowDPType": 1,
        "Path2PartyNowDPLimit": 0,
        "VisMinProfilTemp": 12,
        "VisMaxProfilTemp": 30,
        "VisStepWidthProfilTemp": 1,
        "VisUseSimple": false,
        "HolidayPresentLikeSunday": true,
        "ExtendOverride": false,
        "ThermostatHandlesWindowOpen": false,
        "VisMinDecRelTemp": 1,
        "VisMaxDecRelTemp": 10,
        "VisStepWidthDecRelTemp": 1,
        "VisMinDecAbsTemp": 1,
        "VisMaxDecAbsTemp": 25,
        "VisStepWidthDecAbsTemp": 1,
        "VisMinOverrideTemp": 20,
        "VisMaxOverrideTemp": 30,
        "VisStepWidthOverrideTemp": 1,
        "UseAddTempSensors": false,
        "OverrideMode": 1,
        "UseFireplaceMode": false,
        "UseFireplaceModeResetAt": "22:00",
        "MaintenanceModeTemperature": 32,
        "AddTempSensorsTempLimit": 4,
        "AddTempSensorsMaxTimeDiff": 30,
        "regulatorType": 1,
        "InterActorDelay": 0,
        "InterThermostatDelay": 0,
        "extendedInfoLogTemperature": false,
        "extendedInfoLogActor": false,
        "extendedInfoLogWindow": false,
        "ExtHandlingActorRepTime": 10000,
        "ExtHandlingActorAckWaitTime": 2000,
        "notificationEnabled": false,
        "notificationsType": "Telegram",
        "telegramInstance": "telegram.0",
        "telegramNoticeType": "longTelegramNotice",
        "telegramUser": "All Receiver",
        "telegramSilentNotice": false,
        "telegramOnlyError": false,
        "telegramWaitToSend": 0,
        "whatsappInstance": "whatsapp-cmb.0",
        "whatsappNoticeType": "longWhatsappNotice",
        "whatsappOnlyError": false,
        "whatsappWaitToSend": 0,
        "signalInstance": "signal-cmb.0",
        "signalNoticeType": "longSignalNotice",
        "signalOnlyError": false,
        "signalWaitToSend": 0,
        "pushoverInstance": "pushover.0",
        "pushoverNoticeType": "longPushoverNotice",
        "pushoverSilentNotice": false,
        "pushoverDeviceID": "",
        "pushoverOnlyError": false,
        "pushoverWaitToSend": 0,
        "emailReceiver": "xxx@xxx.com",
        "emailSender": "xxx@xxx.com",
        "emailInstance": "email.0",
        "emailNoticeType": "longEmailNotice",
        "emailOnlyError": false,
        "emailWaitToSend": 0,
        "notificationsTemperature": false,
        "notificationsActor": false,
        "notificationsWindow": false
    }
}